{
  "timestamp": "2025-09-09T03:17:15.725695",
  "players": {
    "player1": {
      "name": "EXPERT_AI_1",
      "elements": [
        "Venom",
        "Fire"
      ],
      "is_ai": true
    },
    "player2": {
      "name": "EXPERT_AI_2",
      "elements": [
        "Lightning",
        "Nectar"
      ],
      "is_ai": true
    }
  },
  "ai_difficulty": "expert",
  "events": [
    {
      "type": "spell_played",
      "player": "EXPERT_AI_1",
      "spell": "Agonize",
      "spell_name": "Agonize",
      "element": "Venom",
      "spell_types": [
        "attack",
        "response",
        "boost"
      ],
      "is_conjury": false,
      "clash": 1,
      "round": 1,
      "timestamp": "2025-09-09T03:17:15.727630"
    },
    {
      "type": "spell_played",
      "player": "EXPERT_AI_2",
      "spell": "Bolts",
      "spell_name": "Bolts",
      "element": "Lightning",
      "spell_types": [
        "attack",
        "boost"
      ],
      "is_conjury": true,
      "clash": 1,
      "round": 1,
      "timestamp": "2025-09-09T03:17:15.727633"
    },
    {
      "type": "response_condition_evaluated",
      "player": "EXPERT_AI_1",
      "spell": "Agonize",
      "condition_met": false,
      "condition_type": "if_spell_advanced_this_turn",
      "clash": 1,
      "round": 1,
      "timestamp": "2025-09-09T03:17:15.727678"
    },
    {
      "type": "weaken_dealt",
      "source_player": "EXPERT_AI_2",
      "target_player": "EXPERT_AI_1",
      "amount": 1,
      "spell": "Bolts",
      "element": "Lightning",
      "clash": 1,
      "round": 1,
      "timestamp": "2025-09-09T03:17:15.727703"
    },
    {
      "type": "spell_advanced",
      "player": "EXPERT_AI_1",
      "spell": "Agonize",
      "from_clash": 1,
      "to_clash": 2,
      "timestamp": "2025-09-09T03:17:15.727718"
    },
    {
      "type": "spell_played",
      "player": "EXPERT_AI_1",
      "spell": "Enfeeble",
      "spell_name": "Enfeeble",
      "element": "Venom",
      "spell_types": [
        "attack",
        "response",
        "boost"
      ],
      "is_conjury": false,
      "clash": 2,
      "round": 1,
      "timestamp": "2025-09-09T03:17:15.729506"
    },
    {
      "type": "spell_played",
      "player": "EXPERT_AI_2",
      "spell": "Absorb",
      "spell_name": "Absorb",
      "element": "Nectar",
      "spell_types": [
        "remedy",
        "response"
      ],
      "is_conjury": false,
      "clash": 2,
      "round": 1,
      "timestamp": "2025-09-09T03:17:15.729514"
    },
    {
      "type": "response_condition_evaluated",
      "player": "EXPERT_AI_2",
      "spell": "Absorb",
      "condition_met": true,
      "condition_type": "if_enemy_has_active_spell_of_type [Looking for attack, found: Agonize(attack,response,boost), Enfeeble(attack,response,boost)]",
      "clash": 2,
      "round": 1,
      "timestamp": "2025-09-09T03:17:15.729567"
    },
    {
      "type": "bolster_done",
      "source_player": "EXPERT_AI_2",
      "target_player": "EXPERT_AI_2",
      "amount": 1,
      "spell": "Absorb",
      "element": "Nectar",
      "clash": 2,
      "round": 1,
      "timestamp": "2025-09-09T03:17:15.729580"
    },
    {
      "type": "healing_done",
      "source_player": "EXPERT_AI_2",
      "target_player": "EXPERT_AI_2",
      "amount": 1,
      "spell": "Absorb",
      "element": "Nectar",
      "clash": 2,
      "round": 1,
      "timestamp": "2025-09-09T03:17:15.729587"
    },
    {
      "type": "response_condition_evaluated",
      "player": "EXPERT_AI_1",
      "spell": "Agonize",
      "condition_met": true,
      "condition_type": "if_spell_advanced_this_turn",
      "clash": 2,
      "round": 1,
      "timestamp": "2025-09-09T03:17:15.729600"
    },
    {
      "type": "damage_dealt",
      "source_player": "EXPERT_AI_1",
      "target_player": "EXPERT_AI_2",
      "amount": 1,
      "spell": "Agonize",
      "element": "Venom",
      "clash": 2,
      "round": 1,
      "is_self_damage": false,
      "timestamp": "2025-09-09T03:17:15.729611"
    },
    {
      "type": "response_condition_evaluated",
      "player": "EXPERT_AI_1",
      "spell": "Enfeeble",
      "condition_met": false,
      "condition_type": "if_enemy_has_active_spell_of_type [Looking for boost, found: none]",
      "clash": 2,
      "round": 1,
      "timestamp": "2025-09-09T03:17:15.729623"
    },
    {
      "type": "spell_advanced",
      "player": "EXPERT_AI_1",
      "spell": "Agonize",
      "from_clash": 2,
      "to_clash": 3,
      "timestamp": "2025-09-09T03:17:15.729638"
    },
    {
      "type": "response_condition_evaluated",
      "player": "EXPERT_AI_1",
      "spell": "Enfeeble",
      "condition_met": false,
      "condition_type": "if_resolve_condition_was_met (advance)",
      "clash": 2,
      "round": 1,
      "timestamp": "2025-09-09T03:17:15.729643"
    },
    {
      "type": "spell_played",
      "player": "EXPERT_AI_1",
      "spell": "Fireball",
      "spell_name": "Fireball",
      "element": "Fire",
      "spell_types": [
        "attack"
      ],
      "is_conjury": false,
      "clash": 3,
      "round": 1,
      "timestamp": "2025-09-09T03:17:15.731075"
    },
    {
      "type": "spell_played",
      "player": "EXPERT_AI_2",
      "spell": "Surge",
      "spell_name": "Surge",
      "element": "Lightning",
      "spell_types": [
        "attack",
        "boost"
      ],
      "is_conjury": false,
      "clash": 3,
      "round": 1,
      "timestamp": "2025-09-09T03:17:15.731078"
    },
    {
      "type": "response_condition_evaluated",
      "player": "EXPERT_AI_1",
      "spell": "Agonize",
      "condition_met": true,
      "condition_type": "if_spell_advanced_this_turn",
      "clash": 3,
      "round": 1,
      "timestamp": "2025-09-09T03:17:15.731119"
    },
    {
      "type": "damage_dealt",
      "source_player": "EXPERT_AI_1",
      "target_player": "EXPERT_AI_2",
      "amount": 1,
      "spell": "Agonize",
      "element": "Venom",
      "clash": 3,
      "round": 1,
      "is_self_damage": false,
      "timestamp": "2025-09-09T03:17:15.731131"
    },
    {
      "type": "damage_dealt",
      "source_player": "EXPERT_AI_2",
      "target_player": "EXPERT_AI_1",
      "amount": 1,
      "spell": "Surge",
      "element": "Lightning",
      "clash": 3,
      "round": 1,
      "is_self_damage": false,
      "timestamp": "2025-09-09T03:17:15.731149"
    },
    {
      "type": "damage_dealt",
      "source_player": "EXPERT_AI_1",
      "target_player": "EXPERT_AI_2",
      "amount": 2,
      "spell": "Fireball",
      "element": "Fire",
      "clash": 3,
      "round": 1,
      "is_self_damage": false,
      "timestamp": "2025-09-09T03:17:15.731167"
    },
    {
      "type": "spell_advanced",
      "player": "EXPERT_AI_1",
      "spell": "Agonize",
      "from_clash": 3,
      "to_clash": 4,
      "timestamp": "2025-09-09T03:17:15.731180"
    },
    {
      "type": "spell_advanced",
      "player": "EXPERT_AI_2",
      "spell": "Surge",
      "from_clash": 3,
      "to_clash": 4,
      "timestamp": "2025-09-09T03:17:15.731188"
    },
    {
      "type": "spell_played",
      "player": "EXPERT_AI_1",
      "spell": "Scorch",
      "spell_name": "Scorch",
      "element": "Fire",
      "spell_types": [
        "attack",
        "boost"
      ],
      "is_conjury": false,
      "clash": 4,
      "round": 1,
      "timestamp": "2025-09-09T03:17:15.731741"
    },
    {
      "type": "response_condition_evaluated",
      "player": "EXPERT_AI_1",
      "spell": "Agonize",
      "condition_met": true,
      "condition_type": "if_spell_advanced_this_turn",
      "clash": 4,
      "round": 1,
      "timestamp": "2025-09-09T03:17:15.731776"
    },
    {
      "type": "damage_dealt",
      "source_player": "EXPERT_AI_1",
      "target_player": "EXPERT_AI_2",
      "amount": 1,
      "spell": "Agonize",
      "element": "Venom",
      "clash": 4,
      "round": 1,
      "is_self_damage": false,
      "timestamp": "2025-09-09T03:17:15.731786"
    },
    {
      "type": "damage_dealt",
      "source_player": "EXPERT_AI_1",
      "target_player": "EXPERT_AI_2",
      "amount": 1,
      "spell": "Scorch",
      "element": "Fire",
      "clash": 4,
      "round": 1,
      "is_self_damage": false,
      "timestamp": "2025-09-09T03:17:15.731806"
    },
    {
      "type": "trunk_lost",
      "player": "EXPERT_AI_2",
      "round": 1,
      "remaining_trunks": 2,
      "timestamp": "2025-09-09T03:17:15.731809",
      "trunk_lifetime_rounds": 0
    },
    {
      "type": "spell_recalled",
      "player": "EXPERT_AI_1",
      "spell": "Ignite",
      "from_location": "discard",
      "timestamp": "2025-09-09T03:17:15.731828"
    },
    {
      "type": "spell_recalled",
      "player": "EXPERT_AI_2",
      "spell": "Electrocute",
      "from_location": "discard",
      "timestamp": "2025-09-09T03:17:15.731834"
    },
    {
      "type": "spell_recalled",
      "player": "EXPERT_AI_2",
      "spell": "Punishment",
      "from_location": "discard",
      "timestamp": "2025-09-09T03:17:15.731837"
    },
    {
      "type": "spell_played",
      "player": "EXPERT_AI_1",
      "spell": "Accelerator",
      "spell_name": "Accelerator",
      "element": "Time",
      "spell_types": [
        "boost"
      ],
      "is_conjury": true,
      "clash": 1,
      "round": 2,
      "timestamp": "2025-09-09T03:17:15.734835"
    },
    {
      "type": "spell_played",
      "player": "EXPERT_AI_2",
      "spell": "Turbulence",
      "spell_name": "Turbulence",
      "element": "Wind",
      "spell_types": [
        "attack",
        "response"
      ],
      "is_conjury": false,
      "clash": 1,
      "round": 2,
      "timestamp": "2025-09-09T03:17:15.734838"
    },
    {
      "type": "response_condition_evaluated",
      "player": "EXPERT_AI_2",
      "spell": "Turbulence",
      "condition_met": false,
      "condition_type": "spell_clashes_count",
      "clash": 1,
      "round": 2,
      "timestamp": "2025-09-09T03:17:15.734887"
    },
    {
      "type": "spell_cancelled",
      "player": "EXPERT_AI_2",
      "spell": "Accelerator",
      "cancelled_by": "Turbulence",
      "timestamp": "2025-09-09T03:17:15.734906"
    },
    {
      "type": "spell_played",
      "player": "EXPERT_AI_1",
      "spell": "Ignite",
      "spell_name": "Ignite",
      "element": "Fire",
      "spell_types": [
        "attack",
        "response",
        "boost"
      ],
      "is_conjury": false,
      "clash": 2,
      "round": 2,
      "timestamp": "2025-09-09T03:17:15.737169"
    },
    {
      "type": "spell_played",
      "player": "EXPERT_AI_2",
      "spell": "Punishment",
      "spell_name": "Punishment",
      "element": "Nectar",
      "spell_types": [
        "attack",
        "response",
        "boost"
      ],
      "is_conjury": true,
      "clash": 2,
      "round": 2,
      "timestamp": "2025-09-09T03:17:15.737172"
    },
    {
      "type": "response_condition_evaluated",
      "player": "EXPERT_AI_1",
      "spell": "Ignite",
      "condition_met": false,
      "condition_type": "if_caster_has_active_spell_of_type",
      "clash": 2,
      "round": 2,
      "timestamp": "2025-09-09T03:17:15.737204"
    },
    {
      "type": "response_condition_evaluated",
      "player": "EXPERT_AI_2",
      "spell": "Punishment",
      "condition_met": true,
      "condition_type": "if_enemy_has_active_spell_of_type [Looking for boost, found: Ignite(attack,response,boost)]",
      "clash": 2,
      "round": 2,
      "timestamp": "2025-09-09T03:17:15.737217"
    },
    {
      "type": "damage_dealt",
      "source_player": "EXPERT_AI_2",
      "target_player": "EXPERT_AI_1",
      "amount": 1,
      "spell": "Punishment",
      "element": "Nectar",
      "clash": 2,
      "round": 2,
      "is_self_damage": false,
      "timestamp": "2025-09-09T03:17:15.737228"
    },
    {
      "type": "spell_advanced",
      "player": "EXPERT_AI_1",
      "spell": "Ignite",
      "from_clash": 2,
      "to_clash": 3,
      "timestamp": "2025-09-09T03:17:15.737240"
    },
    {
      "type": "spell_advanced",
      "player": "EXPERT_AI_2",
      "spell": "Punishment",
      "from_clash": 2,
      "to_clash": 3,
      "timestamp": "2025-09-09T03:17:15.737248"
    },
    {
      "type": "spell_played",
      "player": "EXPERT_AI_1",
      "spell": "Quickshot",
      "spell_name": "Quickshot",
      "element": "Time",
      "spell_types": [
        "attack"
      ],
      "is_conjury": true,
      "clash": 3,
      "round": 2,
      "timestamp": "2025-09-09T03:17:15.739269"
    },
    {
      "type": "spell_played",
      "player": "EXPERT_AI_2",
      "spell": "Blow",
      "spell_name": "Blow",
      "element": "Wind",
      "spell_types": [],
      "is_conjury": false,
      "clash": 3,
      "round": 2,
      "timestamp": "2025-09-09T03:17:15.739272"
    },
    {
      "type": "spell_cancelled",
      "player": "EXPERT_AI_1",
      "spell": "Punishment",
      "cancelled_by": "Quickshot",
      "timestamp": "2025-09-09T03:17:15.739344"
    },
    {
      "type": "damage_dealt",
      "source_player": "EXPERT_AI_1",
      "target_player": "EXPERT_AI_2",
      "amount": 1,
      "spell": "Quickshot",
      "element": "Time",
      "clash": 3,
      "round": 2,
      "is_self_damage": false,
      "timestamp": "2025-09-09T03:17:15.739350"
    },
    {
      "type": "response_condition_evaluated",
      "player": "EXPERT_AI_1",
      "spell": "Ignite",
      "condition_met": true,
      "condition_type": "if_caster_has_active_spell_of_type",
      "clash": 3,
      "round": 2,
      "timestamp": "2025-09-09T03:17:15.739365"
    },
    {
      "type": "damage_dealt",
      "source_player": "EXPERT_AI_1",
      "target_player": "EXPERT_AI_2",
      "amount": 1,
      "spell": "Ignite",
      "element": "Fire",
      "clash": 3,
      "round": 2,
      "is_self_damage": false,
      "timestamp": "2025-09-09T03:17:15.739374"
    },
    {
      "type": "spell_advanced",
      "player": "EXPERT_AI_1",
      "spell": "Ignite",
      "from_clash": 3,
      "to_clash": 4,
      "timestamp": "2025-09-09T03:17:15.739391"
    },
    {
      "type": "spell_advanced",
      "player": "EXPERT_AI_2",
      "spell": "Turbulence",
      "from_clash": 3,
      "to_clash": 4,
      "timestamp": "2025-09-09T03:17:15.739400"
    },
    {
      "type": "spell_played",
      "player": "EXPERT_AI_1",
      "spell": "Repeater",
      "spell_name": "Repeater",
      "element": "Time",
      "spell_types": [
        "boost"
      ],
      "is_conjury": true,
      "clash": 4,
      "round": 2,
      "timestamp": "2025-09-09T03:17:15.740467"
    },
    {
      "type": "spell_played",
      "player": "EXPERT_AI_2",
      "spell": "Electrocute",
      "spell_name": "Electrocute",
      "element": "Lightning",
      "spell_types": [
        "boost"
      ],
      "is_conjury": false,
      "clash": 4,
      "round": 2,
      "timestamp": "2025-09-09T03:17:15.740473"
    },
    {
      "type": "spell_recalled",
      "player": "EXPERT_AI_2",
      "spell": "Blow",
      "from_location": "discard",
      "timestamp": "2025-09-09T03:17:15.740559"
    },
    {
      "type": "response_condition_evaluated",
      "player": "EXPERT_AI_1",
      "spell": "Ignite",
      "condition_met": false,
      "condition_type": "if_caster_has_active_spell_of_type",
      "clash": 4,
      "round": 2,
      "timestamp": "2025-09-09T03:17:15.740580"
    },
    {
      "type": "response_condition_evaluated",
      "player": "EXPERT_AI_2",
      "spell": "Turbulence",
      "condition_met": false,
      "condition_type": "spell_clashes_count",
      "clash": 4,
      "round": 2,
      "timestamp": "2025-09-09T03:17:15.740596"
    },
    {
      "type": "damage_dealt",
      "source_player": "EXPERT_AI_2",
      "target_player": "EXPERT_AI_1",
      "amount": 1,
      "spell": "Turbulence",
      "element": "Wind",
      "clash": 4,
      "round": 2,
      "is_self_damage": false,
      "timestamp": "2025-09-09T03:17:15.740609"
    },
    {
      "type": "spell_recalled",
      "player": "EXPERT_AI_1",
      "spell": "Encumber",
      "from_location": "discard",
      "timestamp": "2025-09-09T03:17:15.740637"
    },
    {
      "type": "spell_recalled",
      "player": "EXPERT_AI_2",
      "spell": "Root",
      "from_location": "discard",
      "timestamp": "2025-09-09T03:17:15.741249"
    },
    {
      "type": "spell_recalled",
      "player": "EXPERT_AI_2",
      "spell": "Bolts",
      "from_location": "discard",
      "timestamp": "2025-09-09T03:17:15.741253"
    },
    {
      "type": "spell_played",
      "player": "EXPERT_AI_1",
      "spell": "Impact",
      "spell_name": "Impact",
      "element": "Space",
      "spell_types": [
        "attack"
      ],
      "is_conjury": true,
      "clash": 1,
      "round": 3,
      "timestamp": "2025-09-09T03:17:15.743810"
    },
    {
      "type": "spell_played",
      "player": "EXPERT_AI_2",
      "spell": "Root",
      "spell_name": "Root",
      "element": "Nectar",
      "spell_types": [
        "boost"
      ],
      "is_conjury": true,
      "clash": 1,
      "round": 3,
      "timestamp": "2025-09-09T03:17:15.743812"
    },
    {
      "type": "damage_dealt",
      "source_player": "EXPERT_AI_1",
      "target_player": "EXPERT_AI_2",
      "amount": 1,
      "spell": "Impact",
      "element": "Space",
      "clash": 1,
      "round": 3,
      "is_self_damage": false,
      "timestamp": "2025-09-09T03:17:15.743858"
    },
    {
      "type": "spell_played",
      "player": "EXPERT_AI_1",
      "spell": "Wormhole",
      "spell_name": "Wormhole",
      "element": "Space",
      "spell_types": [],
      "is_conjury": true,
      "clash": 2,
      "round": 3,
      "timestamp": "2025-09-09T03:17:15.745444"
    },
    {
      "type": "spell_played",
      "player": "EXPERT_AI_2",
      "spell": "Sap",
      "spell_name": "Sap",
      "element": "Shadow",
      "spell_types": [
        "response"
      ],
      "is_conjury": false,
      "clash": 2,
      "round": 3,
      "timestamp": "2025-09-09T03:17:15.745447"
    },
    {
      "type": "response_condition_evaluated",
      "player": "EXPERT_AI_2",
      "spell": "Sap",
      "condition_met": false,
      "condition_type": "if_enemy_has_active_spell_of_type [Looking for boost, found: none]",
      "clash": 2,
      "round": 3,
      "timestamp": "2025-09-09T03:17:15.745475"
    },
    {
      "type": "spell_discarded",
      "player": "EXPERT_AI_1",
      "spell": "Wormhole",
      "discarded_by": "self",
      "timestamp": "2025-09-09T03:17:15.745490"
    },
    {
      "type": "spell_played",
      "player": "EXPERT_AI_1",
      "spell": "Gravitate",
      "spell_name": "Gravitate",
      "element": "Space",
      "spell_types": [],
      "is_conjury": false,
      "clash": 3,
      "round": 3,
      "timestamp": "2025-09-09T03:17:15.746516"
    },
    {
      "type": "spell_played",
      "player": "EXPERT_AI_2",
      "spell": "Familiar",
      "spell_name": "Familiar",
      "element": "Shadow",
      "spell_types": [
        "attack",
        "response"
      ],
      "is_conjury": false,
      "clash": 3,
      "round": 3,
      "timestamp": "2025-09-09T03:17:15.746518"
    },
    {
      "type": "spell_moved",
      "player": "EXPERT_AI_1",
      "spell": "Gravitate",
      "from_clash": 3,
      "to_clash": 4,
      "timestamp": "2025-09-09T03:17:15.746553"
    },
    {
      "type": "response_condition_evaluated",
      "player": "EXPERT_AI_2",
      "spell": "Sap",
      "condition_met": false,
      "condition_type": "if_enemy_has_active_spell_of_type [Looking for boost, found: none]",
      "clash": 3,
      "round": 3,
      "timestamp": "2025-09-09T03:17:15.746562"
    },
    {
      "type": "response_condition_evaluated",
      "player": "EXPERT_AI_2",
      "spell": "Familiar",
      "condition_met": false,
      "condition_type": "if_enemy_has_active_spell_of_type [Looking for attack, found: none]",
      "clash": 3,
      "round": 3,
      "timestamp": "2025-09-09T03:17:15.746572"
    },
    {
      "type": "spell_played",
      "player": "EXPERT_AI_1",
      "spell": "Encumber",
      "spell_name": "Encumber",
      "element": "Venom",
      "spell_types": [
        "response",
        "boost"
      ],
      "is_conjury": false,
      "clash": 4,
      "round": 3,
      "timestamp": "2025-09-09T03:17:15.747430"
    },
    {
      "type": "spell_played",
      "player": "EXPERT_AI_2",
      "spell": "Imitate",
      "spell_name": "Imitate",
      "element": "Shadow",
      "spell_types": [],
      "is_conjury": false,
      "clash": 4,
      "round": 3,
      "timestamp": "2025-09-09T03:17:15.747432"
    },
    {
      "type": "response_condition_evaluated",
      "player": "EXPERT_AI_1",
      "spell": "Encumber",
      "condition_met": false,
      "condition_type": "if_enemy_has_active_spell_of_type [Looking for remedy, found: none]",
      "clash": 4,
      "round": 3,
      "timestamp": "2025-09-09T03:17:15.747490"
    },
    {
      "type": "spell_recalled",
      "player": "EXPERT_AI_1",
      "spell": "Enfeeble",
      "from_location": "discard",
      "timestamp": "2025-09-09T03:17:15.747504"
    },
    {
      "type": "spell_recalled",
      "player": "EXPERT_AI_2",
      "spell": "Absorb",
      "from_location": "discard",
      "timestamp": "2025-09-09T03:17:15.748087"
    },
    {
      "type": "spell_played",
      "player": "EXPERT_AI_1",
      "spell": "Aftershocks",
      "spell_name": "Aftershocks",
      "element": "Earth",
      "spell_types": [
        "attack",
        "response",
        "boost"
      ],
      "is_conjury": true,
      "clash": 1,
      "round": 4,
      "timestamp": "2025-09-09T03:17:15.750660"
    },
    {
      "type": "spell_played",
      "player": "EXPERT_AI_2",
      "spell": "Crepuscule",
      "spell_name": "Crepuscule",
      "element": "Twilight",
      "spell_types": [
        "attack",
        "remedy"
      ],
      "is_conjury": true,
      "clash": 1,
      "round": 4,
      "timestamp": "2025-09-09T03:17:15.750665"
    },
    {
      "type": "response_condition_evaluated",
      "player": "EXPERT_AI_1",
      "spell": "Aftershocks",
      "condition_met": false,
      "condition_type": "if_caster_has_active_spell_of_type",
      "clash": 1,
      "round": 4,
      "timestamp": "2025-09-09T03:17:15.750707"
    },
    {
      "type": "spell_cancelled",
      "player": "EXPERT_AI_2",
      "spell": "Aftershocks",
      "cancelled_by": "Crepuscule",
      "timestamp": "2025-09-09T03:17:15.750739"
    },
    {
      "type": "damage_dealt",
      "source_player": "EXPERT_AI_2",
      "target_player": "EXPERT_AI_1",
      "amount": 1,
      "spell": "Crepuscule",
      "element": "Twilight",
      "clash": 1,
      "round": 4,
      "is_self_damage": false,
      "timestamp": "2025-09-09T03:17:15.750746"
    },
    {
      "type": "trunk_lost",
      "player": "EXPERT_AI_1",
      "round": 4,
      "remaining_trunks": 2,
      "timestamp": "2025-09-09T03:17:15.750749",
      "trunk_lifetime_rounds": 3
    },
    {
      "type": "spell_recalled",
      "player": "EXPERT_AI_1",
      "spell": "Fireball",
      "from_location": "discard",
      "timestamp": "2025-09-09T03:17:15.750965"
    },
    {
      "type": "spell_recalled",
      "player": "EXPERT_AI_1",
      "spell": "Agonize",
      "from_location": "discard",
      "timestamp": "2025-09-09T03:17:15.750969"
    },
    {
      "type": "spell_recalled",
      "player": "EXPERT_AI_2",
      "spell": "Surge",
      "from_location": "discard",
      "timestamp": "2025-09-09T03:17:15.751254"
    },
    {
      "type": "spell_recalled",
      "player": "EXPERT_AI_2",
      "spell": "Punishment",
      "from_location": "discard",
      "timestamp": "2025-09-09T03:17:15.751258"
    },
    {
      "type": "spell_recalled",
      "player": "EXPERT_AI_2",
      "spell": "Turbulence",
      "from_location": "discard",
      "timestamp": "2025-09-09T03:17:15.751260"
    },
    {
      "type": "spell_played",
      "player": "EXPERT_AI_1",
      "spell": "Agonize",
      "spell_name": "Agonize",
      "element": "Venom",
      "spell_types": [
        "attack",
        "response",
        "boost"
      ],
      "is_conjury": false,
      "clash": 1,
      "round": 5,
      "timestamp": "2025-09-09T03:17:15.754750"
    },
    {
      "type": "spell_played",
      "player": "EXPERT_AI_2",
      "spell": "Absorb",
      "spell_name": "Absorb",
      "element": "Nectar",
      "spell_types": [
        "remedy",
        "response"
      ],
      "is_conjury": false,
      "clash": 1,
      "round": 5,
      "timestamp": "2025-09-09T03:17:15.754754"
    },
    {
      "type": "response_condition_evaluated",
      "player": "EXPERT_AI_2",
      "spell": "Absorb",
      "condition_met": true,
      "condition_type": "if_enemy_has_active_spell_of_type [Looking for attack, found: Agonize(attack,response,boost)]",
      "clash": 1,
      "round": 5,
      "timestamp": "2025-09-09T03:17:15.754792"
    },
    {
      "type": "bolster_done",
      "source_player": "EXPERT_AI_2",
      "target_player": "EXPERT_AI_2",
      "amount": 1,
      "spell": "Absorb",
      "element": "Nectar",
      "clash": 1,
      "round": 5,
      "timestamp": "2025-09-09T03:17:15.754803"
    },
    {
      "type": "healing_done",
      "source_player": "EXPERT_AI_2",
      "target_player": "EXPERT_AI_2",
      "amount": 1,
      "spell": "Absorb",
      "element": "Nectar",
      "clash": 1,
      "round": 5,
      "timestamp": "2025-09-09T03:17:15.754809"
    },
    {
      "type": "response_condition_evaluated",
      "player": "EXPERT_AI_1",
      "spell": "Agonize",
      "condition_met": false,
      "condition_type": "if_spell_advanced_this_turn",
      "clash": 1,
      "round": 5,
      "timestamp": "2025-09-09T03:17:15.754820"
    },
    {
      "type": "spell_advanced",
      "player": "EXPERT_AI_1",
      "spell": "Agonize",
      "from_clash": 1,
      "to_clash": 2,
      "timestamp": "2025-09-09T03:17:15.754835"
    },
    {
      "type": "spell_played",
      "player": "EXPERT_AI_1",
      "spell": "Enfeeble",
      "spell_name": "Enfeeble",
      "element": "Venom",
      "spell_types": [
        "attack",
        "response",
        "boost"
      ],
      "is_conjury": false,
      "clash": 2,
      "round": 5,
      "timestamp": "2025-09-09T03:17:15.766999"
    },
    {
      "type": "spell_played",
      "player": "EXPERT_AI_2",
      "spell": "Turbulence",
      "spell_name": "Turbulence",
      "element": "Wind",
      "spell_types": [
        "attack",
        "response"
      ],
      "is_conjury": false,
      "clash": 2,
      "round": 5,
      "timestamp": "2025-09-09T03:17:15.767008"
    },
    {
      "type": "response_condition_evaluated",
      "player": "EXPERT_AI_1",
      "spell": "Agonize",
      "condition_met": true,
      "condition_type": "if_spell_advanced_this_turn",
      "clash": 2,
      "round": 5,
      "timestamp": "2025-09-09T03:17:15.767064"
    },
    {
      "type": "damage_dealt",
      "source_player": "EXPERT_AI_1",
      "target_player": "EXPERT_AI_2",
      "amount": 1,
      "spell": "Agonize",
      "element": "Venom",
      "clash": 2,
      "round": 5,
      "is_self_damage": false,
      "timestamp": "2025-09-09T03:17:15.767084"
    },
    {
      "type": "response_condition_evaluated",
      "player": "EXPERT_AI_2",
      "spell": "Turbulence",
      "condition_met": false,
      "condition_type": "spell_clashes_count",
      "clash": 2,
      "round": 5,
      "timestamp": "2025-09-09T03:17:15.767099"
    },
    {
      "type": "damage_dealt",
      "source_player": "EXPERT_AI_2",
      "target_player": "EXPERT_AI_1",
      "amount": 1,
      "spell": "Turbulence",
      "element": "Wind",
      "clash": 2,
      "round": 5,
      "is_self_damage": false,
      "timestamp": "2025-09-09T03:17:15.767107"
    },
    {
      "type": "response_condition_evaluated",
      "player": "EXPERT_AI_1",
      "spell": "Enfeeble",
      "condition_met": false,
      "condition_type": "if_enemy_has_active_spell_of_type [Looking for boost, found: none]",
      "clash": 2,
      "round": 5,
      "timestamp": "2025-09-09T03:17:15.767118"
    },
    {
      "type": "spell_advanced",
      "player": "EXPERT_AI_1",
      "spell": "Agonize",
      "from_clash": 2,
      "to_clash": 3,
      "timestamp": "2025-09-09T03:17:15.767135"
    },
    {
      "type": "response_condition_evaluated",
      "player": "EXPERT_AI_1",
      "spell": "Enfeeble",
      "condition_met": false,
      "condition_type": "if_resolve_condition_was_met (advance)",
      "clash": 2,
      "round": 5,
      "timestamp": "2025-09-09T03:17:15.767139"
    },
    {
      "type": "spell_played",
      "player": "EXPERT_AI_1",
      "spell": "Quake",
      "spell_name": "Quake",
      "element": "Earth",
      "spell_types": [],
      "is_conjury": false,
      "clash": 3,
      "round": 5,
      "timestamp": "2025-09-09T03:17:15.770289"
    },
    {
      "type": "spell_played",
      "player": "EXPERT_AI_2",
      "spell": "Coalesce",
      "spell_name": "Coalesce",
      "element": "Twilight",
      "spell_types": [
        "boost"
      ],
      "is_conjury": false,
      "clash": 3,
      "round": 5,
      "timestamp": "2025-09-09T03:17:15.770299"
    },
    {
      "type": "response_condition_evaluated",
      "player": "EXPERT_AI_1",
      "spell": "Agonize",
      "condition_met": true,
      "condition_type": "if_spell_advanced_this_turn",
      "clash": 3,
      "round": 5,
      "timestamp": "2025-09-09T03:17:15.770377"
    },
    {
      "type": "damage_dealt",
      "source_player": "EXPERT_AI_1",
      "target_player": "EXPERT_AI_2",
      "amount": 1,
      "spell": "Agonize",
      "element": "Venom",
      "clash": 3,
      "round": 5,
      "is_self_damage": false,
      "timestamp": "2025-09-09T03:17:15.770392"
    },
    {
      "type": "spell_advanced",
      "player": "EXPERT_AI_1",
      "spell": "Agonize",
      "from_clash": 3,
      "to_clash": 4,
      "timestamp": "2025-09-09T03:17:15.770409"
    },
    {
      "type": "spell_advanced",
      "player": "EXPERT_AI_2",
      "spell": "Coalesce",
      "from_clash": 3,
      "to_clash": 4,
      "timestamp": "2025-09-09T03:17:15.770420"
    },
    {
      "type": "spell_played",
      "player": "EXPERT_AI_1",
      "spell": "Fireball",
      "spell_name": "Fireball",
      "element": "Fire",
      "spell_types": [
        "attack"
      ],
      "is_conjury": false,
      "clash": 4,
      "round": 5,
      "timestamp": "2025-09-09T03:17:15.772414"
    },
    {
      "type": "spell_played",
      "player": "EXPERT_AI_2",
      "spell": "Punishment",
      "spell_name": "Punishment",
      "element": "Nectar",
      "spell_types": [
        "attack",
        "response",
        "boost"
      ],
      "is_conjury": true,
      "clash": 4,
      "round": 5,
      "timestamp": "2025-09-09T03:17:15.772422"
    },
    {
      "type": "response_condition_evaluated",
      "player": "EXPERT_AI_1",
      "spell": "Agonize",
      "condition_met": true,
      "condition_type": "if_spell_advanced_this_turn",
      "clash": 4,
      "round": 5,
      "timestamp": "2025-09-09T03:17:15.772487"
    },
    {
      "type": "spell_cancelled",
      "player": "EXPERT_AI_1",
      "spell": "Punishment",
      "cancelled_by": "Agonize",
      "timestamp": "2025-09-09T03:17:15.772507"
    },
    {
      "type": "damage_dealt",
      "source_player": "EXPERT_AI_1",
      "target_player": "EXPERT_AI_2",
      "amount": 2,
      "spell": "Fireball",
      "element": "Fire",
      "clash": 4,
      "round": 5,
      "is_self_damage": false,
      "timestamp": "2025-09-09T03:17:15.772523"
    },
    {
      "type": "trunk_lost",
      "player": "EXPERT_AI_2",
      "round": 5,
      "remaining_trunks": 1,
      "timestamp": "2025-09-09T03:17:15.772527",
      "trunk_lifetime_rounds": 4
    },
    {
      "type": "spell_recalled",
      "player": "EXPERT_AI_1",
      "spell": "Scorch",
      "from_location": "discard",
      "timestamp": "2025-09-09T03:17:15.772631"
    },
    {
      "type": "spell_recalled",
      "player": "EXPERT_AI_1",
      "spell": "Accelerator",
      "from_location": "discard",
      "timestamp": "2025-09-09T03:17:15.772635"
    },
    {
      "type": "spell_recalled",
      "player": "EXPERT_AI_1",
      "spell": "Quickshot",
      "from_location": "discard",
      "timestamp": "2025-09-09T03:17:15.772638"
    },
    {
      "type": "spell_recalled",
      "player": "EXPERT_AI_1",
      "spell": "Ignite",
      "from_location": "discard",
      "timestamp": "2025-09-09T03:17:15.772640"
    },
    {
      "type": "spell_recalled",
      "player": "EXPERT_AI_2",
      "spell": "Electrocute",
      "from_location": "discard",
      "timestamp": "2025-09-09T03:17:15.772648"
    },
    {
      "type": "spell_recalled",
      "player": "EXPERT_AI_2",
      "spell": "Gust",
      "from_location": "discard",
      "timestamp": "2025-09-09T03:17:15.772650"
    },
    {
      "type": "spell_recalled",
      "player": "EXPERT_AI_2",
      "spell": "Blow",
      "from_location": "discard",
      "timestamp": "2025-09-09T03:17:15.772652"
    },
    {
      "type": "spell_played",
      "player": "EXPERT_AI_1",
      "spell": "Ignite",
      "spell_name": "Ignite",
      "element": "Fire",
      "spell_types": [
        "attack",
        "response",
        "boost"
      ],
      "is_conjury": false,
      "clash": 1,
      "round": 6,
      "timestamp": "2025-09-09T03:17:15.777409"
    },
    {
      "type": "spell_played",
      "player": "EXPERT_AI_2",
      "spell": "Starfall",
      "spell_name": "Starfall",
      "element": "Aster",
      "spell_types": [
        "attack",
        "boost"
      ],
      "is_conjury": false,
      "clash": 1,
      "round": 6,
      "timestamp": "2025-09-09T03:17:15.777417"
    },
    {
      "type": "damage_dealt",
      "source_player": "EXPERT_AI_2",
      "target_player": "EXPERT_AI_1",
      "amount": 1,
      "spell": "Starfall",
      "element": "Aster",
      "clash": 1,
      "round": 6,
      "is_self_damage": false,
      "timestamp": "2025-09-09T03:17:15.777475"
    },
    {
      "type": "response_condition_evaluated",
      "player": "EXPERT_AI_1",
      "spell": "Ignite",
      "condition_met": false,
      "condition_type": "if_caster_has_active_spell_of_type",
      "clash": 1,
      "round": 6,
      "timestamp": "2025-09-09T03:17:15.777491"
    },
    {
      "type": "spell_advanced",
      "player": "EXPERT_AI_1",
      "spell": "Ignite",
      "from_clash": 1,
      "to_clash": 2,
      "timestamp": "2025-09-09T03:17:15.777508"
    },
    {
      "type": "spell_advanced",
      "player": "EXPERT_AI_2",
      "spell": "Starfall",
      "from_clash": 1,
      "to_clash": 2,
      "timestamp": "2025-09-09T03:17:15.777516"
    },
    {
      "type": "spell_played",
      "player": "EXPERT_AI_1",
      "spell": "Scorch",
      "spell_name": "Scorch",
      "element": "Fire",
      "spell_types": [
        "attack",
        "boost"
      ],
      "is_conjury": false,
      "clash": 2,
      "round": 6,
      "timestamp": "2025-09-09T03:17:15.781975"
    },
    {
      "type": "spell_played",
      "player": "EXPERT_AI_2",
      "spell": "Gleam",
      "spell_name": "Gleam",
      "element": "Aster",
      "spell_types": [],
      "is_conjury": false,
      "clash": 2,
      "round": 6,
      "timestamp": "2025-09-09T03:17:15.781980"
    },
    {
      "type": "damage_dealt",
      "source_player": "EXPERT_AI_2",
      "target_player": "EXPERT_AI_1",
      "amount": 1,
      "spell": "Starfall",
      "element": "Aster",
      "clash": 2,
      "round": 6,
      "is_self_damage": false,
      "timestamp": "2025-09-09T03:17:15.782035"
    },
    {
      "type": "response_condition_evaluated",
      "player": "EXPERT_AI_1",
      "spell": "Ignite",
      "condition_met": true,
      "condition_type": "if_caster_has_active_spell_of_type",
      "clash": 2,
      "round": 6,
      "timestamp": "2025-09-09T03:17:15.782049"
    },
    {
      "type": "damage_dealt",
      "source_player": "EXPERT_AI_1",
      "target_player": "EXPERT_AI_2",
      "amount": 1,
      "spell": "Ignite",
      "element": "Fire",
      "clash": 2,
      "round": 6,
      "is_self_damage": false,
      "timestamp": "2025-09-09T03:17:15.782058"
    },
    {
      "type": "damage_dealt",
      "source_player": "EXPERT_AI_1",
      "target_player": "EXPERT_AI_2",
      "amount": 1,
      "spell": "Scorch",
      "element": "Fire",
      "clash": 2,
      "round": 6,
      "is_self_damage": false,
      "timestamp": "2025-09-09T03:17:15.782069"
    },
    {
      "type": "spell_advanced",
      "player": "EXPERT_AI_1",
      "spell": "Ignite",
      "from_clash": 2,
      "to_clash": 3,
      "timestamp": "2025-09-09T03:17:15.782085"
    },
    {
      "type": "spell_advanced",
      "player": "EXPERT_AI_2",
      "spell": "Constellation",
      "from_clash": 2,
      "to_clash": 3,
      "timestamp": "2025-09-09T03:17:15.782097"
    },
    {
      "type": "spell_advanced",
      "player": "EXPERT_AI_2",
      "spell": "Electrocute",
      "from_clash": 2,
      "to_clash": 3,
      "timestamp": "2025-09-09T03:17:15.782103"
    },
    {
      "type": "spell_played",
      "player": "EXPERT_AI_1",
      "spell": "Quickshot",
      "spell_name": "Quickshot",
      "element": "Time",
      "spell_types": [
        "attack"
      ],
      "is_conjury": true,
      "clash": 3,
      "round": 6,
      "timestamp": "2025-09-09T03:17:15.783819"
    },
    {
      "type": "spell_played",
      "player": "EXPERT_AI_2",
      "spell": "Constellation",
      "spell_name": "Constellation",
      "element": "Aster",
      "spell_types": [
        "boost"
      ],
      "is_conjury": true,
      "clash": 3,
      "round": 6,
      "timestamp": "2025-09-09T03:17:15.783823"
    },
    {
      "type": "spell_played",
      "player": "EXPERT_AI_2",
      "spell": "Electrocute",
      "spell_name": "Electrocute",
      "element": "Lightning",
      "spell_types": [
        "boost"
      ],
      "is_conjury": false,
      "clash": 3,
      "round": 6,
      "timestamp": "2025-09-09T03:17:15.783824"
    },
    {
      "type": "spell_played",
      "player": "EXPERT_AI_2",
      "spell": "Blow",
      "spell_name": "Blow",
      "element": "Wind",
      "spell_types": [],
      "is_conjury": false,
      "clash": 3,
      "round": 6,
      "timestamp": "2025-09-09T03:17:15.783826"
    },
    {
      "type": "spell_recalled",
      "player": "EXPERT_AI_2",
      "spell": "Starfall",
      "from_location": "discard",
      "timestamp": "2025-09-09T03:17:15.783906"
    },
    {
      "type": "spell_cancelled",
      "player": "EXPERT_AI_1",
      "spell": "Constellation",
      "cancelled_by": "Quickshot",
      "timestamp": "2025-09-09T03:17:15.783933"
    },
    {
      "type": "damage_dealt",
      "source_player": "EXPERT_AI_1",
      "target_player": "EXPERT_AI_2",
      "amount": 1,
      "spell": "Quickshot",
      "element": "Time",
      "clash": 3,
      "round": 6,
      "is_self_damage": false,
      "timestamp": "2025-09-09T03:17:15.783938"
    },
    {
      "type": "response_condition_evaluated",
      "player": "EXPERT_AI_1",
      "spell": "Ignite",
      "condition_met": true,
      "condition_type": "if_caster_has_active_spell_of_type",
      "clash": 3,
      "round": 6,
      "timestamp": "2025-09-09T03:17:15.783953"
    },
    {
      "type": "damage_dealt",
      "source_player": "EXPERT_AI_1",
      "target_player": "EXPERT_AI_2",
      "amount": 1,
      "spell": "Ignite",
      "element": "Fire",
      "clash": 3,
      "round": 6,
      "is_self_damage": false,
      "timestamp": "2025-09-09T03:17:15.783962"
    },
    {
      "type": "spell_advanced",
      "player": "EXPERT_AI_1",
      "spell": "Ignite",
      "from_clash": 3,
      "to_clash": 4,
      "timestamp": "2025-09-09T03:17:15.783980"
    },
    {
      "type": "spell_advanced",
      "player": "EXPERT_AI_2",
      "spell": "Electrocute",
      "from_clash": 3,
      "to_clash": 4,
      "timestamp": "2025-09-09T03:17:15.783989"
    },
    {
      "type": "spell_advanced",
      "player": "EXPERT_AI_2",
      "spell": "Gleam",
      "from_clash": 3,
      "to_clash": 4,
      "timestamp": "2025-09-09T03:17:15.783998"
    },
    {
      "type": "spell_played",
      "player": "EXPERT_AI_1",
      "spell": "Crush",
      "spell_name": "Crush",
      "element": "Earth",
      "spell_types": [
        "attack"
      ],
      "is_conjury": false,
      "clash": 4,
      "round": 6,
      "timestamp": "2025-09-09T03:17:15.785746"
    },
    {
      "type": "spell_played",
      "player": "EXPERT_AI_2",
      "spell": "Starfall",
      "spell_name": "Starfall",
      "element": "Aster",
      "spell_types": [
        "attack",
        "boost"
      ],
      "is_conjury": false,
      "clash": 4,
      "round": 6,
      "timestamp": "2025-09-09T03:17:15.785748"
    },
    {
      "type": "spell_recalled",
      "player": "EXPERT_AI_2",
      "spell": "Constellation",
      "from_location": "discard",
      "timestamp": "2025-09-09T03:17:15.785818"
    },
    {
      "type": "weaken_dealt",
      "source_player": "EXPERT_AI_1",
      "target_player": "EXPERT_AI_2",
      "amount": 1,
      "spell": "Crush",
      "element": "Earth",
      "clash": 4,
      "round": 6,
      "timestamp": "2025-09-09T03:17:15.785835"
    },
    {
      "type": "damage_dealt",
      "source_player": "EXPERT_AI_2",
      "target_player": "EXPERT_AI_1",
      "amount": 1,
      "spell": "Starfall",
      "element": "Aster",
      "clash": 4,
      "round": 6,
      "is_self_damage": false,
      "timestamp": "2025-09-09T03:17:15.785848"
    },
    {
      "type": "trunk_lost",
      "player": "EXPERT_AI_1",
      "round": 6,
      "remaining_trunks": 1,
      "timestamp": "2025-09-09T03:17:15.785851",
      "trunk_lifetime_rounds": 2
    },
    {
      "type": "spell_recalled",
      "player": "EXPERT_AI_1",
      "spell": "Repeater",
      "from_location": "discard",
      "timestamp": "2025-09-09T03:17:15.785870"
    },
    {
      "type": "spell_recalled",
      "player": "EXPERT_AI_1",
      "spell": "Wormhole",
      "from_location": "discard",
      "timestamp": "2025-09-09T03:17:15.785873"
    },
    {
      "type": "spell_recalled",
      "player": "EXPERT_AI_1",
      "spell": "Impact",
      "from_location": "discard",
      "timestamp": "2025-09-09T03:17:15.785876"
    },
    {
      "type": "spell_recalled",
      "player": "EXPERT_AI_2",
      "spell": "Root",
      "from_location": "discard",
      "timestamp": "2025-09-09T03:17:15.786401"
    },
    {
      "type": "spell_recalled",
      "player": "EXPERT_AI_2",
      "spell": "Sap",
      "from_location": "discard",
      "timestamp": "2025-09-09T03:17:15.786405"
    },
    {
      "type": "spell_recalled",
      "player": "EXPERT_AI_2",
      "spell": "Familiar",
      "from_location": "discard",
      "timestamp": "2025-09-09T03:17:15.786408"
    },
    {
      "type": "spell_played",
      "player": "EXPERT_AI_1",
      "spell": "Nightglow",
      "spell_name": "Nightglow",
      "element": "Moonshine",
      "spell_types": [
        "remedy",
        "response",
        "boost"
      ],
      "is_conjury": false,
      "clash": 1,
      "round": 7,
      "timestamp": "2025-09-09T03:17:15.792427"
    },
    {
      "type": "spell_played",
      "player": "EXPERT_AI_2",
      "spell": "Clap",
      "spell_name": "Clap",
      "element": "Thunder",
      "spell_types": [
        "response",
        "boost"
      ],
      "is_conjury": false,
      "clash": 1,
      "round": 7,
      "timestamp": "2025-09-09T03:17:15.792430"
    },
    {
      "type": "response_condition_evaluated",
      "player": "EXPERT_AI_2",
      "spell": "Clap",
      "condition_met": false,
      "condition_type": "if_enemy_has_active_spell_of_type [Looking for any, found: Nightglow(remedy,response,boost)]",
      "clash": 1,
      "round": 7,
      "timestamp": "2025-09-09T03:17:15.792463"
    },
    {
      "type": "bolster_done",
      "source_player": "EXPERT_AI_1",
      "target_player": "EXPERT_AI_1",
      "amount": 1,
      "spell": "Nightglow",
      "element": "Moonshine",
      "clash": 1,
      "round": 7,
      "timestamp": "2025-09-09T03:17:15.792478"
    },
    {
      "type": "response_condition_evaluated",
      "player": "EXPERT_AI_1",
      "spell": "Nightglow",
      "condition_met": false,
      "condition_type": "if_caster_has_active_spell_of_type (advance)",
      "clash": 1,
      "round": 7,
      "timestamp": "2025-09-09T03:17:15.792487"
    },
    {
      "type": "response_condition_evaluated",
      "player": "EXPERT_AI_2",
      "spell": "Clap",
      "condition_met": false,
      "condition_type": "if_resolve_condition_was_met (advance)",
      "clash": 1,
      "round": 7,
      "timestamp": "2025-09-09T03:17:15.792492"
    },
    {
      "type": "spell_played",
      "player": "EXPERT_AI_1",
      "spell": "Slumber",
      "spell_name": "Slumber",
      "element": "Moonshine",
      "spell_types": [
        "remedy",
        "boost"
      ],
      "is_conjury": false,
      "clash": 2,
      "round": 7,
      "timestamp": "2025-09-09T03:17:15.798286"
    },
    {
      "type": "spell_played",
      "player": "EXPERT_AI_2",
      "spell": "Sap",
      "spell_name": "Sap",
      "element": "Shadow",
      "spell_types": [
        "response"
      ],
      "is_conjury": false,
      "clash": 2,
      "round": 7,
      "timestamp": "2025-09-09T03:17:15.798294"
    },
    {
      "type": "response_condition_evaluated",
      "player": "EXPERT_AI_2",
      "spell": "Sap",
      "condition_met": true,
      "condition_type": "if_enemy_has_active_spell_of_type [Looking for boost, found: Slumber(remedy,boost)]",
      "clash": 2,
      "round": 7,
      "timestamp": "2025-09-09T03:17:15.798341"
    },
    {
      "type": "spell_played",
      "player": "EXPERT_AI_1",
      "spell": "Bedim",
      "spell_name": "Bedim",
      "element": "Moonshine",
      "spell_types": [
        "attack",
        "response",
        "boost"
      ],
      "is_conjury": false,
      "clash": 3,
      "round": 7,
      "timestamp": "2025-09-09T03:17:15.800884"
    },
    {
      "type": "spell_played",
      "player": "EXPERT_AI_2",
      "spell": "Slumber",
      "spell_name": "Slumber",
      "element": "Moonshine",
      "spell_types": [
        "remedy",
        "boost"
      ],
      "is_conjury": false,
      "clash": 3,
      "round": 7,
      "timestamp": "2025-09-09T03:17:15.800887"
    },
    {
      "type": "damage_dealt",
      "source_player": "EXPERT_AI_1",
      "target_player": "EXPERT_AI_2",
      "amount": 1,
      "spell": "Bedim",
      "element": "Moonshine",
      "clash": 3,
      "round": 7,
      "is_self_damage": false,
      "timestamp": "2025-09-09T03:17:15.800928"
    },
    {
      "type": "healing_done",
      "source_player": "EXPERT_AI_2",
      "target_player": "EXPERT_AI_2",
      "amount": 1,
      "spell": "Slumber",
      "element": "Moonshine",
      "clash": 3,
      "round": 7,
      "timestamp": "2025-09-09T03:17:15.800946"
    },
    {
      "type": "response_condition_evaluated",
      "player": "EXPERT_AI_1",
      "spell": "Bedim",
      "condition_met": false,
      "condition_type": "if_board_has_active_spell_of_type (advance)",
      "clash": 3,
      "round": 7,
      "timestamp": "2025-09-09T03:17:15.800960"
    },
    {
      "type": "spell_advanced",
      "player": "EXPERT_AI_2",
      "spell": "Slumber",
      "from_clash": 3,
      "to_clash": 4,
      "timestamp": "2025-09-09T03:17:15.800976"
    },
    {
      "type": "spell_played",
      "player": "EXPERT_AI_1",
      "spell": "Impact",
      "spell_name": "Impact",
      "element": "Space",
      "spell_types": [
        "attack"
      ],
      "is_conjury": true,
      "clash": 4,
      "round": 7,
      "timestamp": "2025-09-09T03:17:15.803117"
    },
    {
      "type": "spell_played",
      "player": "EXPERT_AI_2",
      "spell": "Stupefy",
      "spell_name": "Stupefy",
      "element": "Thunder",
      "spell_types": [
        "attack",
        "response"
      ],
      "is_conjury": false,
      "clash": 4,
      "round": 7,
      "timestamp": "2025-09-09T03:17:15.803120"
    },
    {
      "type": "response_condition_evaluated",
      "player": "EXPERT_AI_2",
      "spell": "Stupefy",
      "condition_met": true,
      "condition_type": "if_enemy_has_active_spell_of_type [Looking for attack, found: Impact(attack)]",
      "clash": 4,
      "round": 7,
      "timestamp": "2025-09-09T03:17:15.803164"
    },
    {
      "type": "damage_dealt",
      "source_player": "EXPERT_AI_2",
      "target_player": "EXPERT_AI_1",
      "amount": 2,
      "spell": "Stupefy",
      "element": "Thunder",
      "clash": 4,
      "round": 7,
      "is_self_damage": false,
      "timestamp": "2025-09-09T03:17:15.803182"
    },
    {
      "type": "healing_done",
      "source_player": "EXPERT_AI_2",
      "target_player": "EXPERT_AI_2",
      "amount": 1,
      "spell": "Slumber",
      "element": "Moonshine",
      "clash": 4,
      "round": 7,
      "timestamp": "2025-09-09T03:17:15.803199"
    },
    {
      "type": "spell_recalled",
      "player": "EXPERT_AI_1",
      "spell": "Gravitate",
      "from_location": "discard",
      "timestamp": "2025-09-09T03:17:15.803932"
    },
    {
      "type": "spell_recalled",
      "player": "EXPERT_AI_1",
      "spell": "Encumber",
      "from_location": "discard",
      "timestamp": "2025-09-09T03:17:15.803940"
    },
    {
      "type": "spell_recalled",
      "player": "EXPERT_AI_1",
      "spell": "Aftershocks",
      "from_location": "discard",
      "timestamp": "2025-09-09T03:17:15.803943"
    },
    {
      "type": "spell_recalled",
      "player": "EXPERT_AI_2",
      "spell": "Imitate",
      "from_location": "discard",
      "timestamp": "2025-09-09T03:17:15.804211"
    },
    {
      "type": "spell_recalled",
      "player": "EXPERT_AI_2",
      "spell": "Gravitate",
      "from_location": "discard",
      "timestamp": "2025-09-09T03:17:15.804215"
    },
    {
      "type": "spell_recalled",
      "player": "EXPERT_AI_2",
      "spell": "Bolts",
      "from_location": "discard",
      "timestamp": "2025-09-09T03:17:15.804222"
    },
    {
      "type": "spell_recalled",
      "player": "EXPERT_AI_2",
      "spell": "Crepuscule",
      "from_location": "discard",
      "timestamp": "2025-09-09T03:17:15.804226"
    },
    {
      "type": "spell_played",
      "player": "EXPERT_AI_1",
      "spell": "Grow",
      "spell_name": "Grow",
      "element": "Wood",
      "spell_types": [
        "remedy"
      ],
      "is_conjury": false,
      "clash": 1,
      "round": 8,
      "timestamp": "2025-09-09T03:17:15.810968"
    },
    {
      "type": "spell_played",
      "player": "EXPERT_AI_2",
      "spell": "Crepuscule",
      "spell_name": "Crepuscule",
      "element": "Twilight",
      "spell_types": [
        "attack",
        "remedy"
      ],
      "is_conjury": true,
      "clash": 1,
      "round": 8,
      "timestamp": "2025-09-09T03:17:15.810972"
    },
    {
      "type": "healing_done",
      "source_player": "EXPERT_AI_1",
      "target_player": "EXPERT_AI_1",
      "amount": 1,
      "spell": "Grow",
      "element": "Wood",
      "clash": 1,
      "round": 8,
      "timestamp": "2025-09-09T03:17:15.811014"
    },
    {
      "type": "healing_done",
      "source_player": "EXPERT_AI_2",
      "target_player": "EXPERT_AI_2",
      "amount": 2,
      "spell": "Crepuscule",
      "element": "Twilight",
      "clash": 1,
      "round": 8,
      "timestamp": "2025-09-09T03:17:15.811041"
    },
    {
      "type": "spell_played",
      "player": "EXPERT_AI_1",
      "spell": "Encumber",
      "spell_name": "Encumber",
      "element": "Venom",
      "spell_types": [
        "response",
        "boost"
      ],
      "is_conjury": false,
      "clash": 2,
      "round": 8,
      "timestamp": "2025-09-09T03:17:15.817314"
    },
    {
      "type": "spell_played",
      "player": "EXPERT_AI_2",
      "spell": "Root",
      "spell_name": "Root",
      "element": "Nectar",
      "spell_types": [
        "boost"
      ],
      "is_conjury": true,
      "clash": 2,
      "round": 8,
      "timestamp": "2025-09-09T03:17:15.817317"
    },
    {
      "type": "response_condition_evaluated",
      "player": "EXPERT_AI_1",
      "spell": "Encumber",
      "condition_met": false,
      "condition_type": "if_enemy_has_active_spell_of_type [Looking for remedy, found: none]",
      "clash": 2,
      "round": 8,
      "timestamp": "2025-09-09T03:17:15.817358"
    },
    {
      "type": "response_condition_evaluated",
      "player": "EXPERT_AI_1",
      "spell": "Encumber",
      "condition_met": true,
      "condition_type": "if_not (advance)",
      "clash": 2,
      "round": 8,
      "timestamp": "2025-09-09T03:17:15.817367"
    },
    {
      "type": "spell_advanced",
      "player": "EXPERT_AI_1",
      "spell": "Encumber",
      "from_clash": 2,
      "to_clash": 3,
      "timestamp": "2025-09-09T03:17:15.817379"
    },
    {
      "type": "spell_advanced",
      "player": "EXPERT_AI_2",
      "spell": "Root",
      "from_clash": 2,
      "to_clash": 3,
      "timestamp": "2025-09-09T03:17:15.817387"
    },
    {
      "type": "spell_played",
      "player": "EXPERT_AI_1",
      "spell": "Gravitate",
      "spell_name": "Gravitate",
      "element": "Space",
      "spell_types": [],
      "is_conjury": false,
      "clash": 3,
      "round": 8,
      "timestamp": "2025-09-09T03:17:15.823134"
    },
    {
      "type": "spell_played",
      "player": "EXPERT_AI_2",
      "spell": "Imitate",
      "spell_name": "Imitate",
      "element": "Shadow",
      "spell_types": [],
      "is_conjury": false,
      "clash": 3,
      "round": 8,
      "timestamp": "2025-09-09T03:17:15.823136"
    },
    {
      "type": "spell_moved",
      "player": "EXPERT_AI_2",
      "spell": "Imitate",
      "from_clash": 3,
      "to_clash": 4,
      "timestamp": "2025-09-09T03:17:15.823180"
    },
    {
      "type": "response_condition_evaluated",
      "player": "EXPERT_AI_1",
      "spell": "Encumber",
      "condition_met": false,
      "condition_type": "if_enemy_has_active_spell_of_type [Looking for remedy, found: none]",
      "clash": 3,
      "round": 8,
      "timestamp": "2025-09-09T03:17:15.823199"
    },
    {
      "type": "response_condition_evaluated",
      "player": "EXPERT_AI_1",
      "spell": "Encumber",
      "condition_met": true,
      "condition_type": "if_not (advance)",
      "clash": 3,
      "round": 8,
      "timestamp": "2025-09-09T03:17:15.823208"
    },
    {
      "type": "spell_advanced",
      "player": "EXPERT_AI_1",
      "spell": "Encumber",
      "from_clash": 3,
      "to_clash": 4,
      "timestamp": "2025-09-09T03:17:15.823217"
    },
    {
      "type": "spell_advanced",
      "player": "EXPERT_AI_2",
      "spell": "Root",
      "from_clash": 3,
      "to_clash": 4,
      "timestamp": "2025-09-09T03:17:15.823224"
    },
    {
      "type": "spell_played",
      "player": "EXPERT_AI_1",
      "spell": "Prickle",
      "spell_name": "Prickle",
      "element": "Wood",
      "spell_types": [
        "attack"
      ],
      "is_conjury": false,
      "clash": 4,
      "round": 8,
      "timestamp": "2025-09-09T03:17:15.828885"
    },
    {
      "type": "spell_played",
      "player": "EXPERT_AI_2",
      "spell": "Familiar",
      "spell_name": "Familiar",
      "element": "Shadow",
      "spell_types": [
        "attack",
        "response"
      ],
      "is_conjury": false,
      "clash": 4,
      "round": 8,
      "timestamp": "2025-09-09T03:17:15.828899"
    },
    {
      "type": "response_condition_evaluated",
      "player": "EXPERT_AI_1",
      "spell": "Encumber",
      "condition_met": false,
      "condition_type": "if_enemy_has_active_spell_of_type [Looking for remedy, found: none]",
      "clash": 4,
      "round": 8,
      "timestamp": "2025-09-09T03:17:15.828994"
    },
    {
      "type": "response_condition_evaluated",
      "player": "EXPERT_AI_2",
      "spell": "Encumber",
      "condition_met": false,
      "condition_type": "if_enemy_has_active_spell_of_type [Looking for remedy, found: none]",
      "clash": 4,
      "round": 8,
      "timestamp": "2025-09-09T03:17:15.829005"
    },
    {
      "type": "response_condition_evaluated",
      "player": "EXPERT_AI_2",
      "spell": "Familiar",
      "condition_met": true,
      "condition_type": "if_enemy_has_active_spell_of_type [Looking for attack, found: Prickle(attack)]",
      "clash": 4,
      "round": 8,
      "timestamp": "2025-09-09T03:17:15.829021"
    },
    {
      "type": "spell_cancelled",
      "player": "EXPERT_AI_1",
      "spell": "Root",
      "cancelled_by": "Prickle",
      "timestamp": "2025-09-09T03:17:15.829061"
    },
    {
      "type": "spell_recalled",
      "player": "EXPERT_AI_1",
      "spell": "Enfeeble",
      "from_location": "discard",
      "timestamp": "2025-09-09T03:17:15.829760"
    },
    {
      "type": "spell_recalled",
      "player": "EXPERT_AI_1",
      "spell": "Quake",
      "from_location": "discard",
      "timestamp": "2025-09-09T03:17:15.829763"
    },
    {
      "type": "spell_recalled",
      "player": "EXPERT_AI_1",
      "spell": "Agonize",
      "from_location": "discard",
      "timestamp": "2025-09-09T03:17:15.829767"
    },
    {
      "type": "spell_recalled",
      "player": "EXPERT_AI_2",
      "spell": "Eventide",
      "from_location": "discard",
      "timestamp": "2025-09-09T03:17:15.830178"
    },
    {
      "type": "spell_recalled",
      "player": "EXPERT_AI_2",
      "spell": "Daybreak",
      "from_location": "discard",
      "timestamp": "2025-09-09T03:17:15.830182"
    },
    {
      "type": "spell_recalled",
      "player": "EXPERT_AI_2",
      "spell": "Surge",
      "from_location": "discard",
      "timestamp": "2025-09-09T03:17:15.830186"
    },
    {
      "type": "spell_played",
      "player": "EXPERT_AI_1",
      "spell": "Defend",
      "spell_name": "Defend",
      "element": "Metal",
      "spell_types": [
        "remedy",
        "response",
        "boost"
      ],
      "is_conjury": false,
      "clash": 1,
      "round": 9,
      "timestamp": "2025-09-09T03:17:15.836910"
    },
    {
      "type": "spell_played",
      "player": "EXPERT_AI_2",
      "spell": "Flow",
      "spell_name": "Flow",
      "element": "Water",
      "spell_types": [
        "remedy",
        "response",
        "boost"
      ],
      "is_conjury": false,
      "clash": 1,
      "round": 9,
      "timestamp": "2025-09-09T03:17:15.836915"
    },
    {
      "type": "response_condition_evaluated",
      "player": "EXPERT_AI_2",
      "spell": "Flow",
      "condition_met": false,
      "condition_type": "if_caster_has_active_spell_of_type",
      "clash": 1,
      "round": 9,
      "timestamp": "2025-09-09T03:17:15.836960"
    },
    {
      "type": "response_condition_evaluated",
      "player": "EXPERT_AI_1",
      "spell": "Defend",
      "condition_met": false,
      "condition_type": "if_caster_has_active_spell_of_type",
      "clash": 1,
      "round": 9,
      "timestamp": "2025-09-09T03:17:15.836973"
    },
    {
      "type": "spell_advanced",
      "player": "EXPERT_AI_1",
      "spell": "Defend",
      "from_clash": 1,
      "to_clash": 2,
      "timestamp": "2025-09-09T03:17:15.836989"
    },
    {
      "type": "spell_advanced",
      "player": "EXPERT_AI_2",
      "spell": "Flow",
      "from_clash": 1,
      "to_clash": 2,
      "timestamp": "2025-09-09T03:17:15.836996"
    },
    {
      "type": "spell_played",
      "player": "EXPERT_AI_1",
      "spell": "Reinforce",
      "spell_name": "Reinforce",
      "element": "Metal",
      "spell_types": [
        "remedy"
      ],
      "is_conjury": false,
      "clash": 2,
      "round": 9,
      "timestamp": "2025-09-09T03:17:15.843288"
    },
    {
      "type": "spell_played",
      "player": "EXPERT_AI_2",
      "spell": "Nourish",
      "spell_name": "Nourish",
      "element": "Water",
      "spell_types": [
        "remedy"
      ],
      "is_conjury": false,
      "clash": 2,
      "round": 9,
      "timestamp": "2025-09-09T03:17:15.843293"
    },
    {
      "type": "bolster_done",
      "source_player": "EXPERT_AI_1",
      "target_player": "EXPERT_AI_1",
      "amount": 1,
      "spell": "Reinforce",
      "element": "Metal",
      "clash": 2,
      "round": 9,
      "timestamp": "2025-09-09T03:17:15.843338"
    },
    {
      "type": "response_condition_evaluated",
      "player": "EXPERT_AI_2",
      "spell": "Flow",
      "condition_met": true,
      "condition_type": "if_caster_has_active_spell_of_type",
      "clash": 2,
      "round": 9,
      "timestamp": "2025-09-09T03:17:15.843352"
    },
    {
      "type": "healing_done",
      "source_player": "EXPERT_AI_2",
      "target_player": "EXPERT_AI_2",
      "amount": 1,
      "spell": "Flow",
      "element": "Water",
      "clash": 2,
      "round": 9,
      "timestamp": "2025-09-09T03:17:15.843360"
    },
    {
      "type": "healing_done",
      "source_player": "EXPERT_AI_2",
      "target_player": "EXPERT_AI_2",
      "amount": 2,
      "spell": "Nourish",
      "element": "Water",
      "clash": 2,
      "round": 9,
      "timestamp": "2025-09-09T03:17:15.843369"
    },
    {
      "type": "response_condition_evaluated",
      "player": "EXPERT_AI_1",
      "spell": "Defend",
      "condition_met": false,
      "condition_type": "if_caster_has_active_spell_of_type",
      "clash": 2,
      "round": 9,
      "timestamp": "2025-09-09T03:17:15.843379"
    },
    {
      "type": "spell_advanced",
      "player": "EXPERT_AI_1",
      "spell": "Defend",
      "from_clash": 2,
      "to_clash": 3,
      "timestamp": "2025-09-09T03:17:15.843392"
    },
    {
      "type": "spell_advanced",
      "player": "EXPERT_AI_2",
      "spell": "Flow",
      "from_clash": 2,
      "to_clash": 3,
      "timestamp": "2025-09-09T03:17:15.843399"
    },
    {
      "type": "spell_played",
      "player": "EXPERT_AI_1",
      "spell": "Quake",
      "spell_name": "Quake",
      "element": "Earth",
      "spell_types": [],
      "is_conjury": false,
      "clash": 3,
      "round": 9,
      "timestamp": "2025-09-09T03:17:15.849350"
    },
    {
      "type": "spell_played",
      "player": "EXPERT_AI_2",
      "spell": "Daybreak",
      "spell_name": "Daybreak",
      "element": "Twilight",
      "spell_types": [],
      "is_conjury": false,
      "clash": 3,
      "round": 9,
      "timestamp": "2025-09-09T03:17:15.849354"
    },
    {
      "type": "spell_recalled",
      "player": "EXPERT_AI_2",
      "spell": "Nourish",
      "from_location": "discard",
      "timestamp": "2025-09-09T03:17:15.849411"
    },
    {
      "type": "response_condition_evaluated",
      "player": "EXPERT_AI_2",
      "spell": "Flow",
      "condition_met": false,
      "condition_type": "if_caster_has_active_spell_of_type",
      "clash": 3,
      "round": 9,
      "timestamp": "2025-09-09T03:17:15.849434"
    },
    {
      "type": "response_condition_evaluated",
      "player": "EXPERT_AI_1",
      "spell": "Defend",
      "condition_met": false,
      "condition_type": "if_caster_has_active_spell_of_type",
      "clash": 3,
      "round": 9,
      "timestamp": "2025-09-09T03:17:15.849446"
    },
    {
      "type": "spell_advanced",
      "player": "EXPERT_AI_1",
      "spell": "Defend",
      "from_clash": 3,
      "to_clash": 4,
      "timestamp": "2025-09-09T03:17:15.849460"
    },
    {
      "type": "spell_advanced",
      "player": "EXPERT_AI_2",
      "spell": "Flow",
      "from_clash": 3,
      "to_clash": 4,
      "timestamp": "2025-09-09T03:17:15.849466"
    },
    {
      "type": "spell_played",
      "player": "EXPERT_AI_1",
      "spell": "Besiege",
      "spell_name": "Besiege",
      "element": "Metal",
      "spell_types": [
        "attack",
        "response",
        "boost"
      ],
      "is_conjury": false,
      "clash": 4,
      "round": 9,
      "timestamp": "2025-09-09T03:17:15.853733"
    },
    {
      "type": "spell_played",
      "player": "EXPERT_AI_2",
      "spell": "Nourish",
      "spell_name": "Nourish",
      "element": "Water",
      "spell_types": [
        "remedy"
      ],
      "is_conjury": false,
      "clash": 4,
      "round": 9,
      "timestamp": "2025-09-09T03:17:15.853735"
    },
    {
      "type": "response_condition_evaluated",
      "player": "EXPERT_AI_2",
      "spell": "Flow",
      "condition_met": true,
      "condition_type": "if_caster_has_active_spell_of_type",
      "clash": 4,
      "round": 9,
      "timestamp": "2025-09-09T03:17:15.853777"
    },
    {
      "type": "healing_done",
      "source_player": "EXPERT_AI_2",
      "target_player": "EXPERT_AI_2",
      "amount": 1,
      "spell": "Flow",
      "element": "Water",
      "clash": 4,
      "round": 9,
      "timestamp": "2025-09-09T03:17:15.853785"
    },
    {
      "type": "healing_done",
      "source_player": "EXPERT_AI_2",
      "target_player": "EXPERT_AI_2",
      "amount": 2,
      "spell": "Nourish",
      "element": "Water",
      "clash": 4,
      "round": 9,
      "timestamp": "2025-09-09T03:17:15.853794"
    },
    {
      "type": "response_condition_evaluated",
      "player": "EXPERT_AI_1",
      "spell": "Defend",
      "condition_met": true,
      "condition_type": "if_caster_has_active_spell_of_type",
      "clash": 4,
      "round": 9,
      "timestamp": "2025-09-09T03:17:15.853804"
    },
    {
      "type": "healing_done",
      "source_player": "EXPERT_AI_1",
      "target_player": "EXPERT_AI_1",
      "amount": 1,
      "spell": "Defend",
      "element": "Metal",
      "clash": 4,
      "round": 9,
      "timestamp": "2025-09-09T03:17:15.853811"
    },
    {
      "type": "response_condition_evaluated",
      "player": "EXPERT_AI_1",
      "spell": "Besiege",
      "condition_met": true,
      "condition_type": "if_caster_has_active_spell_of_type",
      "clash": 4,
      "round": 9,
      "timestamp": "2025-09-09T03:17:15.853829"
    },
    {
      "type": "damage_dealt",
      "source_player": "EXPERT_AI_1",
      "target_player": "EXPERT_AI_2",
      "amount": 1,
      "spell": "Besiege",
      "element": "Metal",
      "clash": 4,
      "round": 9,
      "is_self_damage": false,
      "timestamp": "2025-09-09T03:17:15.853839"
    },
    {
      "type": "spell_recalled",
      "player": "EXPERT_AI_1",
      "spell": "Fireball",
      "from_location": "discard",
      "timestamp": "2025-09-09T03:17:15.854320"
    },
    {
      "type": "spell_recalled",
      "player": "EXPERT_AI_1",
      "spell": "Accelerator",
      "from_location": "discard",
      "timestamp": "2025-09-09T03:17:15.854324"
    },
    {
      "type": "spell_recalled",
      "player": "EXPERT_AI_1",
      "spell": "Scorch",
      "from_location": "discard",
      "timestamp": "2025-09-09T03:17:15.854326"
    },
    {
      "type": "spell_recalled",
      "player": "EXPERT_AI_2",
      "spell": "Absorb",
      "from_location": "discard",
      "timestamp": "2025-09-09T03:17:15.854645"
    },
    {
      "type": "spell_recalled",
      "player": "EXPERT_AI_2",
      "spell": "Turbulence",
      "from_location": "discard",
      "timestamp": "2025-09-09T03:17:15.854648"
    },
    {
      "type": "spell_recalled",
      "player": "EXPERT_AI_2",
      "spell": "Coalesce",
      "from_location": "discard",
      "timestamp": "2025-09-09T03:17:15.854652"
    },
    {
      "type": "spell_played",
      "player": "EXPERT_AI_1",
      "spell": "Accelerator",
      "spell_name": "Accelerator",
      "element": "Time",
      "spell_types": [
        "boost"
      ],
      "is_conjury": true,
      "clash": 1,
      "round": 10,
      "timestamp": "2025-09-09T03:17:15.860470"
    },
    {
      "type": "spell_played",
      "player": "EXPERT_AI_2",
      "spell": "Turbulence",
      "spell_name": "Turbulence",
      "element": "Wind",
      "spell_types": [
        "attack",
        "response"
      ],
      "is_conjury": false,
      "clash": 1,
      "round": 10,
      "timestamp": "2025-09-09T03:17:15.860474"
    },
    {
      "type": "response_condition_evaluated",
      "player": "EXPERT_AI_2",
      "spell": "Turbulence",
      "condition_met": false,
      "condition_type": "spell_clashes_count",
      "clash": 1,
      "round": 10,
      "timestamp": "2025-09-09T03:17:15.860519"
    },
    {
      "type": "spell_cancelled",
      "player": "EXPERT_AI_2",
      "spell": "Accelerator",
      "cancelled_by": "Turbulence",
      "timestamp": "2025-09-09T03:17:15.860538"
    },
    {
      "type": "spell_played",
      "player": "EXPERT_AI_1",
      "spell": "Fireball",
      "spell_name": "Fireball",
      "element": "Fire",
      "spell_types": [
        "attack"
      ],
      "is_conjury": false,
      "clash": 2,
      "round": 10,
      "timestamp": "2025-09-09T03:17:15.864852"
    },
    {
      "type": "spell_played",
      "player": "EXPERT_AI_2",
      "spell": "Illuminate",
      "spell_name": "Illuminate",
      "element": "Sunbeam",
      "spell_types": [],
      "is_conjury": false,
      "clash": 2,
      "round": 10,
      "timestamp": "2025-09-09T03:17:15.864855"
    },
    {
      "type": "damage_dealt",
      "source_player": "EXPERT_AI_1",
      "target_player": "EXPERT_AI_2",
      "amount": 2,
      "spell": "Fireball",
      "element": "Fire",
      "clash": 2,
      "round": 10,
      "is_self_damage": false,
      "timestamp": "2025-09-09T03:17:15.864896"
    },
    {
      "type": "response_condition_evaluated",
      "player": "EXPERT_AI_2",
      "spell": "Reflect",
      "condition_met": true,
      "condition_type": "if_enemy_has_active_spell_of_type [Looking for attack, found: Fireball(attack)]",
      "clash": 2,
      "round": 10,
      "timestamp": "2025-09-09T03:17:15.864908"
    },
    {
      "type": "damage_dealt",
      "source_player": "EXPERT_AI_2",
      "target_player": "EXPERT_AI_1",
      "amount": 3,
      "spell": "Reflect",
      "element": "Sunbeam",
      "clash": 2,
      "round": 10,
      "is_self_damage": false,
      "timestamp": "2025-09-09T03:17:15.864916"
    },
    {
      "type": "spell_played",
      "player": "EXPERT_AI_1",
      "spell": "Scorch",
      "spell_name": "Scorch",
      "element": "Fire",
      "spell_types": [
        "attack",
        "boost"
      ],
      "is_conjury": false,
      "clash": 3,
      "round": 10,
      "timestamp": "2025-09-09T03:17:15.868716"
    },
    {
      "type": "spell_played",
      "player": "EXPERT_AI_2",
      "spell": "Absorb",
      "spell_name": "Absorb",
      "element": "Nectar",
      "spell_types": [
        "remedy",
        "response"
      ],
      "is_conjury": false,
      "clash": 3,
      "round": 10,
      "timestamp": "2025-09-09T03:17:15.868719"
    },
    {
      "type": "response_condition_evaluated",
      "player": "EXPERT_AI_2",
      "spell": "Absorb",
      "condition_met": true,
      "condition_type": "if_enemy_has_active_spell_of_type [Looking for attack, found: Scorch(attack,boost)]",
      "clash": 3,
      "round": 10,
      "timestamp": "2025-09-09T03:17:15.868752"
    },
    {
      "type": "bolster_done",
      "source_player": "EXPERT_AI_2",
      "target_player": "EXPERT_AI_2",
      "amount": 1,
      "spell": "Absorb",
      "element": "Nectar",
      "clash": 3,
      "round": 10,
      "timestamp": "2025-09-09T03:17:15.868760"
    },
    {
      "type": "healing_done",
      "source_player": "EXPERT_AI_2",
      "target_player": "EXPERT_AI_2",
      "amount": 1,
      "spell": "Absorb",
      "element": "Nectar",
      "clash": 3,
      "round": 10,
      "timestamp": "2025-09-09T03:17:15.868766"
    },
    {
      "type": "damage_dealt",
      "source_player": "EXPERT_AI_1",
      "target_player": "EXPERT_AI_2",
      "amount": 1,
      "spell": "Scorch",
      "element": "Fire",
      "clash": 3,
      "round": 10,
      "is_self_damage": false,
      "timestamp": "2025-09-09T03:17:15.868781"
    },
    {
      "type": "spell_played",
      "player": "EXPERT_AI_1",
      "spell": "Renew",
      "spell_name": "Renew",
      "element": "Ichor",
      "spell_types": [
        "remedy"
      ],
      "is_conjury": true,
      "clash": 4,
      "round": 10,
      "timestamp": "2025-09-09T03:17:15.872402"
    },
    {
      "type": "spell_played",
      "player": "EXPERT_AI_2",
      "spell": "Glare",
      "spell_name": "Glare",
      "element": "Sunbeam",
      "spell_types": [
        "attack"
      ],
      "is_conjury": true,
      "clash": 4,
      "round": 10,
      "timestamp": "2025-09-09T03:17:15.872405"
    },
    {
      "type": "bolster_done",
      "source_player": "EXPERT_AI_1",
      "target_player": "EXPERT_AI_1",
      "amount": 1,
      "spell": "Renew",
      "element": "Ichor",
      "clash": 4,
      "round": 10,
      "timestamp": "2025-09-09T03:17:15.872441"
    },
    {
      "type": "healing_done",
      "source_player": "EXPERT_AI_1",
      "target_player": "EXPERT_AI_1",
      "amount": 1,
      "spell": "Renew",
      "element": "Ichor",
      "clash": 4,
      "round": 10,
      "timestamp": "2025-09-09T03:17:15.872446"
    },
    {
      "type": "damage_dealt",
      "source_player": "EXPERT_AI_2",
      "target_player": "EXPERT_AI_1",
      "amount": 1,
      "spell": "Glare",
      "element": "Sunbeam",
      "clash": 4,
      "round": 10,
      "is_self_damage": false,
      "timestamp": "2025-09-09T03:17:15.872468"
    },
    {
      "type": "spell_recalled",
      "player": "EXPERT_AI_1",
      "spell": "Quickshot",
      "from_location": "discard",
      "timestamp": "2025-09-09T03:17:15.872790"
    },
    {
      "type": "spell_recalled",
      "player": "EXPERT_AI_1",
      "spell": "Ignite",
      "from_location": "discard",
      "timestamp": "2025-09-09T03:17:15.872793"
    },
    {
      "type": "spell_recalled",
      "player": "EXPERT_AI_1",
      "spell": "Crush",
      "from_location": "discard",
      "timestamp": "2025-09-09T03:17:15.872795"
    },
    {
      "type": "spell_recalled",
      "player": "EXPERT_AI_2",
      "spell": "Punishment",
      "from_location": "discard",
      "timestamp": "2025-09-09T03:17:15.872861"
    },
    {
      "type": "spell_recalled",
      "player": "EXPERT_AI_2",
      "spell": "Blow",
      "from_location": "discard",
      "timestamp": "2025-09-09T03:17:15.872863"
    },
    {
      "type": "spell_recalled",
      "player": "EXPERT_AI_2",
      "spell": "Electrocute",
      "from_location": "discard",
      "timestamp": "2025-09-09T03:17:15.872867"
    },
    {
      "type": "spell_recalled",
      "player": "EXPERT_AI_2",
      "spell": "Gleam",
      "from_location": "discard",
      "timestamp": "2025-09-09T03:17:15.872870"
    },
    {
      "type": "spell_recalled",
      "player": "EXPERT_AI_2",
      "spell": "Starfall",
      "from_location": "discard",
      "timestamp": "2025-09-09T03:17:15.872873"
    },
    {
      "type": "spell_played",
      "player": "EXPERT_AI_1",
      "spell": "Overexert",
      "spell_name": "Overexert",
      "element": "Blood",
      "spell_types": [],
      "is_conjury": false,
      "clash": 1,
      "round": 11,
      "timestamp": "2025-09-09T03:17:15.879756"
    },
    {
      "type": "spell_played",
      "player": "EXPERT_AI_2",
      "spell": "Punishment",
      "spell_name": "Punishment",
      "element": "Nectar",
      "spell_types": [
        "attack",
        "response",
        "boost"
      ],
      "is_conjury": true,
      "clash": 1,
      "round": 11,
      "timestamp": "2025-09-09T03:17:15.879758"
    },
    {
      "type": "damage_dealt",
      "source_player": "EXPERT_AI_1",
      "target_player": "EXPERT_AI_1",
      "amount": 1,
      "spell": "Overexert",
      "element": "Blood",
      "clash": 1,
      "round": 11,
      "is_self_damage": true,
      "timestamp": "2025-09-09T03:17:15.879810"
    },
    {
      "type": "trunk_lost",
      "player": "EXPERT_AI_1",
      "round": 11,
      "remaining_trunks": 0,
      "timestamp": "2025-09-09T03:17:15.879817",
      "trunk_lifetime_rounds": 5
    }
  ],
  "player_elements": {
    "EXPERT_AI_1": [
      "Venom",
      "Fire"
    ],
    "EXPERT_AI_2": [
      "Lightning",
      "Nectar"
    ]
  },
  "winner": "EXPERT_AI_2",
  "total_rounds": 10,
  "result": {
    "winner": "EXPERT_AI_2",
    "winner_health": 2,
    "loser_health": 0,
    "total_rounds": 10,
    "end_timestamp": "2025-09-09T03:17:15.879830"
  }
}